fashion_mnist_ore/__init__.py
fashion_mnist_ore/install_asset.py
fashion_mnist_ore-0.1.0.dist-info/METADATA
fashion_mnist_ore-0.1.0.dist-info/WHEEL
fashion_mnist_ore-0.1.0.dist-info/entry_points.txt
fashion_mnist_ore-0.1.0.dist-info/top_level.txt
fashion_mnist_ore-0.1.0.dist-info/RECORD
