Metadata-Version: 2.4
Name: fashion-mnist-ore
Version: 0.1.0
Summary: Loader that assembles a zstd-sharded binary asset and restores the original file
Author: OREYH
Requires-Python: >=3.8
Requires-Dist: fashion-mnist-ore-shard01==0.1.0
Requires-Dist: zstandard>=0.22.0
